IMG2PPM/__init__.py
IMG2PPM-0.0.1.dist-info/LICENSE
IMG2PPM-0.0.1.dist-info/METADATA
IMG2PPM-0.0.1.dist-info/WHEEL
IMG2PPM-0.0.1.dist-info/top_level.txt
IMG2PPM-0.0.1.dist-info/RECORD
